opsys_led_panel/__init__.py
opsys_led_panel/led_panel_abstract.py
opsys_led_panel/led_panel_controller.py
opsys_led_panel-0.0.4.dist-info/LICENSE
opsys_led_panel-0.0.4.dist-info/METADATA
opsys_led_panel-0.0.4.dist-info/WHEEL
opsys_led_panel-0.0.4.dist-info/top_level.txt
opsys_led_panel-0.0.4.dist-info/RECORD
