Metadata-Version: 2.1
Name: opsys-led-panel
Version: 0.0.4
Summary: python package for led panel device control
Home-page: https://bitbucket.org/opsys_tech/opsys-led-panel/src/master/
Download-URL: https://bitbucket.org/opsys_tech/opsys-led-panel/src/master/
Author: dmitry.borovensky
Author-email: dmitry.borovensky@opsys-tech.com
License-File: LICENSE
